flow3d/__init__.py
flow3d/flow3d.py
flow3d/job.py
flow3d/prepin.py
flow3d/simulation.py
flow3d/data/__init__.py
flow3d/data/template/__init__.py
flow3d/data/template/limits.txt
flow3d/data/template/other.txt
flow3d/data/template/xput.txt
flow3d/data/template/material/CMSX-4.txt
flow3d/data/template/material/Cu10Sn.txt
flow3d/data/template/material/UNS_A03590.txt
flow3d/data/template/material/UNS_A97075.txt
flow3d/data/template/material/UNS_N06002.txt
flow3d/data/template/material/UNS_N07718.txt
flow3d/data/template/material/UNS_R56400.txt
flow3d/data/template/material/UNS_S30400.txt
flow3d/data/template/material/UNS_S31603.txt
flow3d/data/template/material/__init__.py
Flow3D-0.0.11.dist-info/LICENSE
Flow3D-0.0.11.dist-info/METADATA
Flow3D-0.0.11.dist-info/WHEEL
Flow3D-0.0.11.dist-info/top_level.txt
Flow3D-0.0.11.dist-info/RECORD
