Metadata-Version: 2.1
Name: Flow3D
Version: 0.0.11
Summary: Python wrapper for Flow3D
Author-email: Peter Pak <ppak10@gmail.com>
Project-URL: Homepage, https://github.com/ppak10/Flow3D
Project-URL: Issues, https://github.com/ppak10/Flow3D/issues
Classifier: Programming Language :: Python :: 3
Classifier: License :: OSI Approved :: MIT License
Classifier: Operating System :: OS Independent
Requires-Python: >=3.10
License-File: LICENSE
